anti_fraud/__init__.py
anti_fraud/module_01.py
anti_fraud-0.0.1.dist-info/LICENSE
anti_fraud-0.0.1.dist-info/METADATA
anti_fraud-0.0.1.dist-info/WHEEL
anti_fraud-0.0.1.dist-info/top_level.txt
anti_fraud-0.0.1.dist-info/RECORD
