Metadata-Version: 2.1
Name: anti-fraud
Version: 0.0.1
Summary: tony反欺诈函数
Home-page: UNKNOWN
Author: Tony
Author-email: tony_antifraud@126.com
License: UNKNOWN
Platform: UNKNOWN
Classifier: Programming Language :: Python :: 3
Classifier: License :: OSI Approved :: MIT License
Classifier: Operating System :: OS Independent
Requires-Python: >=3.6
License-File: LICENSE
Requires-Dist: pandas
Requires-Dist: numpy
